vii_sdk/__init__.py
vii_sdk/address.py
vii_sdk/asset.py
vii_sdk/base58.py
vii_sdk/builder.py
vii_sdk/exceptions.py
vii_sdk/federation.py
vii_sdk/horizon.py
vii_sdk/keypair.py
vii_sdk/memo.py
vii_sdk/network.py
vii_sdk/operation.py
vii_sdk/purecrc16.py
vii_sdk/transaction.py
vii_sdk/transaction_envelope.py
vii_sdk/utils.py
vii_sdk/version.py
vii_sdk/viixdr/ViiXDR_const.py
vii_sdk/viixdr/ViiXDR_pack.py
vii_sdk/viixdr/ViiXDR_type.py
vii_sdk/viixdr/__init__.py
vii_sdk/wordlist/chinese.txt
vii_sdk-1.0.0.dist-info/LICENSE
vii_sdk-1.0.0.dist-info/METADATA
vii_sdk-1.0.0.dist-info/WHEEL
vii_sdk-1.0.0.dist-info/top_level.txt
vii_sdk-1.0.0.dist-info/RECORD
